<?xml version="1.0" ?>
<LanguageData>
  <!-- EN: Overrides some precepts related to -->
  <OverridesSomePrecepts>Substitui alguns preceitos relacionados com</OverridesSomePrecepts>
  <!-- EN: Agrees with memes -->
  <AgreeableMemes>Acordos com memes</AgreeableMemes>
  <!-- EN: Conflicts with memes -->
  <DisagreeableMemes>Conflitos com memes</DisagreeableMemes>
  <!-- EN: Slave -->
  <TabSlave>Escravo</TabSlave>
  <!-- EN: The faction goodwill you will gain if you release a slave. This is affected by the slaves's physical and mental health. -->
  <SlaveReleaseRelationGainsDesc>A boa vontade de facção ganhará se libertar um escravo. Isso é afetado pela saúde física e mental dos escravos.</SlaveReleaseRelationGainsDesc>
  <!-- EN: Relations gain on release -->
  <SlaveReleasePotentialRelationGains>Ganho de relações de libertação</SlaveReleasePotentialRelationGains>
  <!-- EN: Slave rebellion interval -->
  <SlaveRebellionMTBDays>Intervalo de rebelião eslava</SlaveRebellionMTBDays>
  <!-- EN: The average number of days between slave rebellion attempts. Only time awake is counted. This is affected by suppression, mood, health, proximity to weapons, the number of slaves on the map, and the presence of colonists on the map. -->
  <SlaveRebellionMTBDaysDescription>O número médio de dias entre tentativas de rebelião de escravos. Só o tempo acordado é contado. Isso é afetado pela supressão, humor, saúde, proximidade com armas, o número de escravos no mapa e a presença de colonos no mapa.</SlaveRebellionMTBDaysDescription>
  <!-- EN: Suppression -->
  <Suppression>Supressão</Suppression>
  <!-- EN: Suppression is the psychological effect of fear and control on a slave. If suppression is low, slaves are more likely to rebel. -->
  <SuppressionDesc>A supressão é o efeito psicológico do medo e do controle sobre um escravo. Se a supressão é baixa, os escravos são mais propensos a se rebelar.</SuppressionDesc>
  <!-- EN: Suppression fall rate -->
  <SuppressionFallRate>Taxa de queda de supressão</SuppressionFallRate>
  <!-- EN: Suppression falls over time depending on its current level:\n\n- {1}+ suppression: {0} per day\n- {4}-{3} suppression: {2} per day\n- {6}- suppression: {5} per day\n\nApparel and terror can also affect the suppression fall rate. This slave's fall rate calculation is -->
  <SuppressionFallRateDesc>Supressão cai ao longo do tempo dependendo do seu nível atual:\n\n- Supressão. {0} por dia\n- Supressão: {2} por dia\n- Supressão. {5} por dia\n\nO vestuário e o terror também podem afetar a taxa de queda de supressão. O cálculo da taxa de queda deste escravo é</SuppressionFallRateDesc>
  <!-- EN: Cannot emancipate -->
  <CannotEmancipate>Não pode emancipar</CannotEmancipate>
  <!-- EN: Cannot imprison -->
  <CannotImprison>Não pode aprisionar</CannotImprison>
  <!-- EN: Current suppression -->
  <CurrentSuppression>Supressão de corrente</CurrentSuppression>
  <!-- EN: Terror -->
  <Terror>Terror</Terror>
  <!-- EN: Terror is a way to keep slaves suppressed. It rises when the slave spends time near terrifying things like terror sculptures. A slave can only be affected by three terror sources at a time.\n\nWhile terror is high, suppression falls slower as follows -->
  <TerrorDescription>Terror é uma maneira de manter os escravos suprimidos. Ele sobe quando o escravo passa tempo perto de coisas aterrorizantes como esculturas de terror. Um escravo só pode ser afetado por três fontes de terror de cada vez.\n\nEnquanto o terror é alto, a supressão cai mais devagar da seguinte maneira</TerrorDescription>
  <!-- EN: Recent terrifying observations -->
  <TerrorCurrentThoughts>Observações terríveis recentes</TerrorCurrentThoughts>
  <!-- EN: Base interval -->
  <SuppressionBaseInterval>Intervalo base</SuppressionBaseInterval>
  <!-- EN: Moving capacity -->
  <SuppressionMovingCapacityFactor>Capacidade de movimento</SuppressionMovingCapacityFactor>
  <!-- EN: Suppression -->
  <SuppressionFactor>Supressão</SuppressionFactor>
  <!-- EN: Mood -->
  <SuppressionMoodFactor>Humor</SuppressionMoodFactor>
  <!-- EN: Slave count -->
  <SuppressionSlaveCountFactor>Contagem de escravos</SuppressionSlaveCountFactor>
  <!-- EN: Escape route -->
  <SuppressionEscapeFactor>Rota de fuga</SuppressionEscapeFactor>
  <!-- EN: Weapon proximity -->
  <SuppressionWeaponProximityFactor>Proximidade de arma</SuppressionWeaponProximityFactor>
  <!-- EN: Final interval -->
  <SuppressionFinalInterval>Intervalo final</SuppressionFinalInterval>
  <!-- EN: Unattended -->
  <SuppressionUnattendedByColonists>Destinados</SuppressionUnattendedByColonists>
  <!-- EN: At least one of the {0} slaves on this map is expected rebel on average every {1}. -->
  <SuppressionRebellionAnySlave>Pelo menos um dos {0} escravos neste mapa é esperado rebelde em média cada {1}.</SuppressionRebellionAnySlave>
  <!-- EN: Will -->
  <WillLevel>Will</WillLevel>
  <!-- EN: How much the prisoner is determined not to submit. When this reaches zero, they can be enslaved. -->
  <WillLevelDesc>Quanto o prisioneiro está determinado a não se submeter. Quando isso atinge zero, eles podem ser escravizados.</WillLevelDesc>
  <!-- EN: {0} base will -->
  <WillFromPawnKind>{0} base will</WillFromPawnKind>
  <!-- EN: Target ideoligion -->
  <IdeoConversionTarget>Orientação do alvo</IdeoConversionTarget>
  <!-- EN: The ideoligion your wardens will attempt to convert this prisoner to. -->
  <IdeoConversionTargetDesc>O ideoligion seus diretores tentarão converter este prisioneiro para.</IdeoConversionTargetDesc>
  <!-- EN: Change per day due to mood -->
  <CertaintyChangePerDay>Mudança por dia devido ao humor</CertaintyChangePerDay>
  <!-- EN: Change rate based on mood -->
  <MoodChangeRate>Taxa de mudança com base no humor</MoodChangeRate>
  <!-- EN: {PAWN_nameDef}'s certainty in {IDEO_name} -->
  <CertaintyInIdeo>{PAWN_name Def} a certeza em {IDEO_name}</CertaintyInIdeo>
  <!-- EN: A special status this person holds in their ideoligion. If you change or take away this role, they will become unhappy. -->
  <RoleDesc>Um estatuto especial que esta pessoa tem na sua orientação. Se você mudar ou tirar este papel, eles se tornarão infelizes.</RoleDesc>
  <!-- EN: Changing roles requires a role change ritual. Select any ritual spot or altar and press 'Begin role change'. -->
  <RoleAssignmentTip>Mudar papéis requer um ritual de mudança de papel. Selecione qualquer local ritual ou altar e pressione 'Begin papel change'.</RoleAssignmentTip>
  <!-- EN: Conversion attempts will be weaker because of trait/meme agreement -->
  <ConversionWeakerDueToTraitAgreements>As tentativas de conversão serão mais fracas devido ao acordo de traços/mememe</ConversionWeakerDueToTraitAgreements>
  <!-- EN: Conversion attempts will be stronger because of trait/meme conflict -->
  <ConversionStrongerDueToTraitAgreements>As tentativas de conversão serão mais fortes por causa do conflito de traços/mememe</ConversionStrongerDueToTraitAgreements>
  <!-- EN: Cut -->
  <Cut>Corta</Cut>
  <!-- EN: Cut both eyes -->
  <CutBothEyes>Cortar os olhos</CutBothEyes>
</LanguageData>
